nutree/__init__.py
nutree/common.py
nutree/diff.py
nutree/dot.py
nutree/fs.py
nutree/mermaid.py
nutree/node.py
nutree/py.typed
nutree/rdf.py
nutree/tree.py
nutree/tree_generator.py
nutree/typed_tree.py
nutree-1.0.0.data/data/CHANGELOG.md
nutree-1.0.0.dist-info/LICENSE.txt
nutree-1.0.0.dist-info/METADATA
nutree-1.0.0.dist-info/WHEEL
nutree-1.0.0.dist-info/top_level.txt
nutree-1.0.0.dist-info/RECORD
