Metadata-Version: 2.1
Name: nutree
Version: 1.0.0
Summary: A Python library for tree data structures with an intuitive, yet powerful, API.
Home-page: https://github.com/mar10/nutree/
Author: Martin Wendt
Author-email: nutree@wwwendt.de
Maintainer: Martin Wendt
Maintainer-email: nutree@wwwendt.de
License: MIT
Project-URL: Bug Tracker, https://github.com/mar10/nutree/issues
Project-URL: Source Code, https://github.com/mar10/nutree
Project-URL: Documentation, https://nutree.readthedocs.io/
Project-URL: Download, https://github.com/mar10/nutree/releases/latest
Keywords: tree,data structure,digraph,graph,nodes,hierarchy,treelib
Classifier: Development Status :: 5 - Production/Stable
Classifier: Environment :: Console
Classifier: Intended Audience :: Developers
Classifier: License :: OSI Approved :: MIT License
Classifier: Operating System :: OS Independent
Classifier: Programming Language :: Python
Classifier: Programming Language :: Python :: 3
Classifier: Programming Language :: Python :: 3 :: Only
Classifier: Programming Language :: Python :: 3.9
Classifier: Programming Language :: Python :: 3.10
Classifier: Programming Language :: Python :: 3.11
Classifier: Programming Language :: Python :: 3.12
Classifier: Programming Language :: Python :: 3.13
Classifier: Topic :: Software Development :: Libraries :: Python Modules
License-File: LICENSE.txt
Requires-Dist: typing_extensions>=4.0
Provides-Extra: graph
Requires-Dist: pydot; extra == "graph"
Requires-Dist: rdflib; extra == "graph"
Requires-Dist: graphviz; extra == "graph"
Provides-Extra: random
Requires-Dist: fabulist; extra == "random"
Provides-Extra: all
Requires-Dist: pydot; extra == "all"
Requires-Dist: rdflib; extra == "all"
Requires-Dist: graphviz; extra == "all"
Requires-Dist: fabulist; extra == "all"
